tests/__init__.py
tests/test_api_key_management.py
tests/test_connection_manager.py
tests/test_health_checks.py
tests/test_integration.py
tests/test_server.py
vectara_mcp/__init__.py
vectara_mcp/__main__.py
vectara_mcp/_version.py
vectara_mcp/auth.py
vectara_mcp/connection_manager.py
vectara_mcp/health_checks.py
vectara_mcp/server.py
vectara_mcp-0.2.1.dist-info/LICENSE
vectara_mcp-0.2.1.dist-info/METADATA
vectara_mcp-0.2.1.dist-info/WHEEL
vectara_mcp-0.2.1.dist-info/entry_points.txt
vectara_mcp-0.2.1.dist-info/top_level.txt
vectara_mcp-0.2.1.dist-info/RECORD
