Metadata-Version: 2.1
Name: vectara-mcp
Version: 0.2.1
Summary: A Model Context Protocol (MCP) server that provides tools from Vectara
Home-page: https://github.com/vectara/vectara-mcp
Author: Ofer Mendelevitch
Author-email: ofer@vectara.com
Project-URL: Bug Reports, https://github.com/vectara/vectara-mcp/issues
Project-URL: Source, https://github.com/vectara/vectara-mcp
Keywords: vectara,mcp,rag,ai,search,semantic-search
Classifier: Development Status :: 4 - Beta
Classifier: Intended Audience :: Developers
Classifier: License :: OSI Approved :: Apache Software License
Classifier: Operating System :: OS Independent
Classifier: Programming Language :: Python :: 3.11
Classifier: Topic :: Software Development :: Libraries :: Python Modules
Classifier: Topic :: Text Processing :: Linguistic
Requires-Python: >=3.11
License-File: LICENSE
Requires-Dist: mcp>=1.6.0
Requires-Dist: fastmcp>=0.4.1
Requires-Dist: fastapi>=0.95.0
Requires-Dist: uvicorn>=0.34.0
Requires-Dist: aiohttp>=3.8.0
Requires-Dist: tenacity>=8.0.0
Requires-Dist: python-dotenv>=1.0.0
Provides-Extra: test
Requires-Dist: pytest>=7.0.0; extra == "test"
Requires-Dist: pytest-asyncio>=0.21.0; extra == "test"
Requires-Dist: pytest-cov>=4.0.0; extra == "test"
Requires-Dist: python-dotenv>=1.0.0; extra == "test"
Requires-Dist: pylint>=3.0.0; extra == "test"
